omniconfig/__init__.py
omniconfig/args.py
omniconfig/configclass.py
omniconfig/parser.py
omniconfig/utils.py
omniconfig/version.py
omniconfig-0.1.10.dist-info/LICENSE
omniconfig-0.1.10.dist-info/METADATA
omniconfig-0.1.10.dist-info/WHEEL
omniconfig-0.1.10.dist-info/RECORD
