Metadata-Version: 2.1
Name: omniconfig
Version: 0.1.10
Summary: Python package for parsing configurations from YAML and TOML and command-line interface.
License: Apache-2.0
Author: Yujun Lin
Requires-Python: >=3.10
Classifier: License :: OSI Approved :: Apache Software License
Classifier: Programming Language :: Python :: 3
Classifier: Programming Language :: Python :: 3.10
Classifier: Programming Language :: Python :: 3.11
Classifier: Programming Language :: Python :: 3.12
Requires-Dist: PyYAML (>=6.0)
Requires-Dist: docstring-parser (>=0.15)
Requires-Dist: toml (>=0.10)
